ob.py
nexas.egg-info/PKG-INFO
nexas.egg-info/SOURCES.txt
nexas.egg-info/dependency_links.txt
nexas.egg-info/requires.txt
nexas.egg-info/top_level.txt