Metadata-Version: 2.1
Name: nexas
Version: 1.0.0
Summary: twitch aio
Author: vexin
